splat/__init__.py
splat/__main__.py
splat/py.typed
splat/disassembler/__init__.py
splat/disassembler/disassembler.py
splat/disassembler/disassembler_instance.py
splat/disassembler/disassembler_section.py
splat/disassembler/null_disassembler.py
splat/disassembler/spimdisasm_disassembler.py
splat/platforms/__init__.py
splat/platforms/n64.py
splat/platforms/ps2.py
splat/platforms/psp.py
splat/platforms/psx.py
splat/scripts/__init__.py
splat/scripts/capy.py
splat/scripts/create_config.py
splat/scripts/split.py
splat/segtypes/__init__.py
splat/segtypes/linker_entry.py
splat/segtypes/segment.py
splat/segtypes/common/__init__.py
splat/segtypes/common/asm.py
splat/segtypes/common/asmtu.py
splat/segtypes/common/bin.py
splat/segtypes/common/bss.py
splat/segtypes/common/c.py
splat/segtypes/common/code.py
splat/segtypes/common/codesubsegment.py
splat/segtypes/common/cpp.py
splat/segtypes/common/data.py
splat/segtypes/common/databin.py
splat/segtypes/common/eh_frame.py
splat/segtypes/common/gcc_except_table.py
splat/segtypes/common/group.py
splat/segtypes/common/hasm.py
splat/segtypes/common/header.py
splat/segtypes/common/lib.py
splat/segtypes/common/linker_offset.py
splat/segtypes/common/pad.py
splat/segtypes/common/rdata.py
splat/segtypes/common/rodata.py
splat/segtypes/common/rodatabin.py
splat/segtypes/common/sbss.py
splat/segtypes/common/sdata.py
splat/segtypes/common/segment.py
splat/segtypes/common/textbin.py
splat/segtypes/n64/__init__.py
splat/segtypes/n64/ci.py
splat/segtypes/n64/ci4.py
splat/segtypes/n64/ci8.py
splat/segtypes/n64/decompressor.py
splat/segtypes/n64/gfx.py
splat/segtypes/n64/header.py
splat/segtypes/n64/i1.py
splat/segtypes/n64/i4.py
splat/segtypes/n64/i8.py
splat/segtypes/n64/ia16.py
splat/segtypes/n64/ia4.py
splat/segtypes/n64/ia8.py
splat/segtypes/n64/img.py
splat/segtypes/n64/ipl3.py
splat/segtypes/n64/mio0.py
splat/segtypes/n64/palette.py
splat/segtypes/n64/rgba16.py
splat/segtypes/n64/rgba32.py
splat/segtypes/n64/rsp.py
splat/segtypes/n64/vtx.py
splat64-0.37.2.dist-info/METADATA
splat64-0.37.2.dist-info/WHEEL
splat64-0.37.2.dist-info/entry_points.txt
splat64-0.37.2.dist-info/licenses/LICENSE
splat64-0.37.2.dist-info/RECORD
