Metadata-Version: 2.4
Name: splat64
Version: 0.37.2
Summary: A binary splitting tool to assist with decompilation and modding projects
Project-URL: Repository, https://github.com/ethteck/splat
Project-URL: Issues, https://github.com/ethteck/splat/issues
Project-URL: Changelog, https://github.com/ethteck/splat/blob/master/CHANGELOG.md
License: MIT License
License-File: LICENSE
Classifier: License :: OSI Approved :: MIT License
Classifier: Programming Language :: Python :: 3
Requires-Python: >=3.9
Requires-Dist: colorama==0.4.6
Requires-Dist: intervaltree==3.1.0
Requires-Dist: pylibyaml==0.1.0
Requires-Dist: pyyaml==6.0.3
Requires-Dist: tqdm==4.67.1
Provides-Extra: dev
Requires-Dist: crunch64<1.0.0,>=0.5.1; extra == 'dev'
Requires-Dist: mypy; extra == 'dev'
Requires-Dist: n64img>=0.3.3; extra == 'dev'
Requires-Dist: pygfxd>=1.0.5; extra == 'dev'
Requires-Dist: rabbitizer<2.0.0,>=1.12.0; extra == 'dev'
Requires-Dist: ruff; extra == 'dev'
Requires-Dist: spimdisasm<2.0.0,>=1.39.0; extra == 'dev'
Requires-Dist: types-colorama; extra == 'dev'
Requires-Dist: types-pyyaml; extra == 'dev'
Provides-Extra: mips
Requires-Dist: crunch64<1.0.0,>=0.5.1; extra == 'mips'
Requires-Dist: n64img>=0.3.3; extra == 'mips'
Requires-Dist: pygfxd>=1.0.5; extra == 'mips'
Requires-Dist: rabbitizer<2.0.0,>=1.12.0; extra == 'mips'
Requires-Dist: spimdisasm<2.0.0,>=1.39.0; extra == 'mips'
